immich_mcp/__init__.py
immich_mcp/immich_api.py
immich_mcp/main.py
immich_mcp/server.py
immich_mcp-0.5.7.dist-info/METADATA
immich_mcp-0.5.7.dist-info/WHEEL
immich_mcp-0.5.7.dist-info/licenses/LICENSE
immich_mcp-0.5.7.dist-info/RECORD
