Metadata-Version: 2.4
Name: immich-mcp
Version: 0.5.7
Summary: An MCP server for Immich.
Project-URL: Repository, https://github.com/immich-app/immich-mcp
Project-URL: Issues, https://github.com/immich-app/immich-mcp/issues
License-File: LICENSE
Classifier: Programming Language :: Python :: 3
Classifier: Programming Language :: Python :: 3.11
Classifier: Programming Language :: Python :: 3.12
Classifier: Programming Language :: Python :: 3.13
Requires-Python: >=3.11
Requires-Dist: gunicorn
Requires-Dist: mcp
Requires-Dist: uvicorn
Provides-Extra: dev
Requires-Dist: mcp[cli]; extra == 'dev'
Requires-Dist: pre-commit; extra == 'dev'
Requires-Dist: pydantic-ai-slim[mcp]; extra == 'dev'
Requires-Dist: pytest; extra == 'dev'
Requires-Dist: pytest-asyncio; extra == 'dev'
Requires-Dist: pytest-mock; extra == 'dev'
Requires-Dist: ruff; extra == 'dev'
